ansys/grantami/bomanalytics_openapi/__init__.py
ansys/grantami/bomanalytics_openapi/py.typed
ansys/grantami/bomanalytics_openapi/v1/__init__.py
ansys/grantami/bomanalytics_openapi/v1/api/__init__.py
ansys/grantami/bomanalytics_openapi/v1/api/compliance_api.py
ansys/grantami/bomanalytics_openapi/v1/api/documentation_api.py
ansys/grantami/bomanalytics_openapi/v1/api/impacted_substances_api.py
ansys/grantami/bomanalytics_openapi/v1/api/licenses_api.py
ansys/grantami/bomanalytics_openapi/v1/api/sustainability_api.py
ansys/grantami/bomanalytics_openapi/v1/models/__init__.py
ansys/grantami/bomanalytics_openapi/v1/models/common_coating_with_compliance.py
ansys/grantami/bomanalytics_openapi/v1/models/common_impacted_substance.py
ansys/grantami/bomanalytics_openapi/v1/models/common_indicator_definition.py
ansys/grantami/bomanalytics_openapi/v1/models/common_indicator_result.py
ansys/grantami/bomanalytics_openapi/v1/models/common_legislation_with_impacted_substances.py
ansys/grantami/bomanalytics_openapi/v1/models/common_log_entry.py
ansys/grantami/bomanalytics_openapi/v1/models/common_material_reference.py
ansys/grantami/bomanalytics_openapi/v1/models/common_material_with_compliance.py
ansys/grantami/bomanalytics_openapi/v1/models/common_part_reference.py
ansys/grantami/bomanalytics_openapi/v1/models/common_part_with_compliance.py
ansys/grantami/bomanalytics_openapi/v1/models/common_preferred_units.py
ansys/grantami/bomanalytics_openapi/v1/models/common_process_reference.py
ansys/grantami/bomanalytics_openapi/v1/models/common_request_config.py
ansys/grantami/bomanalytics_openapi/v1/models/common_specification_reference.py
ansys/grantami/bomanalytics_openapi/v1/models/common_specification_with_compliance.py
ansys/grantami/bomanalytics_openapi/v1/models/common_substance_with_compliance.py
ansys/grantami/bomanalytics_openapi/v1/models/common_sustainability_material_contributing_component.py
ansys/grantami/bomanalytics_openapi/v1/models/common_sustainability_material_summary.py
ansys_grantami_bomanalytics_openapi-5.0.0.dist-info/METADATA
ansys_grantami_bomanalytics_openapi-5.0.0.dist-info/WHEEL
ansys_grantami_bomanalytics_openapi-5.0.0.dist-info/licenses/LICENSE
ansys_grantami_bomanalytics_openapi-5.0.0.dist-info/RECORD
