Metadata-Version: 2.4
Name: ansys-grantami-bomanalytics-openapi
Version: 5.0.0
Summary: Autogenerated client library for the Granta MI BoM Analytics Services.
License: MIT
License-File: LICENSE
Keywords: Ansys,OpenAPI
Author: ANSYS, Inc.
Author-email: pyansys.core@ansys.com
Maintainer: ANSYS, Inc.
Maintainer-email: pyansys.core@ansys.com
Requires-Python: >=3.10.0,<4.0.0
Classifier: Development Status :: 5 - Production/Stable
Classifier: Intended Audience :: Science/Research
Classifier: License :: OSI Approved :: MIT License
Classifier: Operating System :: OS Independent
Classifier: Programming Language :: Python :: 3
Classifier: Programming Language :: Python :: 3.10
Classifier: Programming Language :: Python :: 3.11
Classifier: Programming Language :: Python :: 3.12
Classifier: Programming Language :: Python :: 3.13
Classifier: Programming Language :: Python :: 3.14
Classifier: Topic :: Scientific/Engineering :: Information Analysis
Requires-Dist: ansys-openapi-common (>=2.2.2,<3.0.0)
Requires-Dist: python-dateutil (>=2.8.2,<3.0.0)
Requires-Dist: requests (>=2.26.0,<3.0.0)
Project-URL: Documentation, https://grantami.docs.pyansys.com
Project-URL: Homepage, https://github.com/ansys/grantami-bomanalytics-openapi
